globalmart_api/__init__.py
globalmart_api/oops.py
nivedita_globalmart_api-0.1.dist-info/License.txt
nivedita_globalmart_api-0.1.dist-info/METADATA
nivedita_globalmart_api-0.1.dist-info/WHEEL
nivedita_globalmart_api-0.1.dist-info/top_level.txt
nivedita_globalmart_api-0.1.dist-info/RECORD
